{"ProjectBreakpoints":"{\"Value\":{\"Google/GetCalendar.xaml\":[{\"ConditionalExpression\":null,\"ActionExpression\":null,\"ExpectedHitCounter\":null,\"ShouldContinueAfterAction\":false,\"BreakpointType\":1,\"LocationIdentifier\":\"Select Item 'Montharrow_drop_down'\",\"IsEnabled\":false,\"Annotation\":null,\"Id\":\"45d5bb79-43dd-4212-8bad-f5c74767f0d7\",\"ActivityIdRef\":\"NSelectItem_1\",\"ActivityId\":\"1.629\",\"ActivityName\":\"Select Item 'Montharrow_drop_down'\",\"IsTransient\":false},{\"ConditionalExpression\":null,\"ActionExpression\":null,\"ExpectedHitCounter\":null,\"ShouldContinueAfterAction\":false,\"BreakpointType\":1,\"LocationIdentifier\":\"Extract Table Data\",\"IsEnabled\":false,\"Annotation\":null,\"Id\":\"83d46d40-6061-44f8-b91d-20456fd5d11a\",\"ActivityIdRef\":\"NExtractData_1\",\"ActivityId\":\"1.543\",\"ActivityName\":\"Extract Table Data\",\"IsTransient\":false},{\"ConditionalExpression\":null,\"ActionExpression\":null,\"ExpectedHitCounter\":null,\"ShouldContinueAfterAction\":false,\"BreakpointType\":1,\"LocationIdentifier\":\"LogFile - Invoke Workflow File (LogFile\\\\LogFile.xaml)\",\"IsEnabled\":false,\"Annotation\":null,\"Id\":\"6be458d1-5b05-4290-8a6b-b924c52c202a\",\"ActivityIdRef\":\"InvokeWorkflowFile_4\",\"ActivityId\":\"1.426\",\"ActivityName\":\"LogFile - Invoke Workflow File (LogFile\\\\LogFile.xaml)\",\"IsTransient\":false},{\"ConditionalExpression\":null,\"ActionExpression\":null,\"ExpectedHitCounter\":null,\"ShouldContinueAfterAction\":false,\"BreakpointType\":1,\"LocationIdentifier\":\"Assign\",\"IsEnabled\":true,\"Annotation\":null,\"Id\":\"e8cd7575-5a7b-473c-af98-954696930722\",\"ActivityIdRef\":\"Assign_6\",\"ActivityId\":\"1.222\",\"ActivityName\":\"Assign\",\"IsTransient\":false},{\"ConditionalExpression\":null,\"ActionExpression\":null,\"ExpectedHitCounter\":null,\"ShouldContinueAfterAction\":false,\"BreakpointType\":1,\"LocationIdentifier\":\"Assign\",\"IsEnabled\":true,\"Annotation\":null,\"Id\":\"c739fd44-52bc-41f1-a6a1-c9cc035c86c3\",\"ActivityIdRef\":\"Assign_9\",\"ActivityId\":\"1.161\",\"ActivityName\":\"Assign\",\"IsTransient\":false},{\"ConditionalExpression\":null,\"ActionExpression\":null,\"ExpectedHitCounter\":null,\"ShouldContinueAfterAction\":false,\"BreakpointType\":1,\"LocationIdentifier\":\"Assign\",\"IsEnabled\":true,\"Annotation\":null,\"Id\":\"b40a9953-6118-42e0-b4ca-2e63f89ff296\",\"ActivityIdRef\":\"Assign_10\",\"ActivityId\":\"1.114\",\"ActivityName\":\"Assign\",\"IsTransient\":false}],\"Google/GetCalendarAPI.xaml\":[{\"ConditionalExpression\":null,\"ActionExpression\":null,\"ExpectedHitCounter\":null,\"ShouldContinueAfterAction\":false,\"BreakpointType\":1,\"LocationIdentifier\":\"Log Message\",\"IsEnabled\":true,\"Annotation\":null,\"Id\":\"bf6e36f4-8f8c-4759-8400-2a6020a8996b\",\"ActivityIdRef\":\"LogMessage_1\",\"ActivityId\":\"1.2\",\"ActivityName\":\"Log Message\",\"IsTransient\":false}]},\"CodeBreakpoints\":{}}","OpenedDocuments":"[{\"DocumentPath\":\"Main.xaml\",\"FactoryId\":\"{ACB8E7BA-F093-44C1-9B50-33ECA51AAE16}\"}]","ProjectActivitiesViewState":"{\"Google/GetCalendar.xaml\":[{\"ActivityIdRef\":\"LogMessage_2\",\"IsAdvancedOptionsExpanded\":false,\"Widgets\":{}},{\"ActivityIdRef\":\"InvokeWorkflowFile_1\",\"IsAdvancedOptionsExpanded\":false,\"Categories\":{\"Common\":true,\"Options\":true,\"Log\":true},\"Widgets\":{}},{\"ActivityIdRef\":\"OutputDataTable_1\",\"IsAdvancedOptionsExpanded\":false,\"Widgets\":{}},{\"ActivityIdRef\":\"ForEach`1_3\",\"IsAdvancedOptionsExpanded\":false,\"Categories\":{\"\":true},\"Widgets\":{\"Body\":{\"ShowExpanded\":true}}},{\"ActivityIdRef\":\"InvokeWorkflowFile_4\",\"IsAdvancedOptionsExpanded\":false,\"Categories\":{\"Common\":true,\"Options\":true,\"Log\":true},\"Widgets\":{}},{\"ActivityIdRef\":\"If_1\",\"IsAdvancedOptionsExpanded\":false,\"Widgets\":{\"Then\":{\"ShowExpanded\":true},\"Else\":{\"ShowExpanded\":true}}},{\"ActivityIdRef\":\"AddDataRow_1\",\"IsAdvancedOptionsExpanded\":false,\"Widgets\":{}},{\"ActivityIdRef\":\"AddQueueItem_1\",\"IsAdvancedOptionsExpanded\":false,\"Categories\":{\"Input\":true,\"Misc\":true},\"Widgets\":{}},{\"ActivityIdRef\":\"LogMessage_7\",\"IsAdvancedOptionsExpanded\":false,\"Widgets\":{}},{\"ActivityIdRef\":\"InvokeWorkflowFile_3\",\"IsAdvancedOptionsExpanded\":false,\"Categories\":{\"Common\":true,\"Options\":true,\"Log\":true},\"Widgets\":{}},{\"ActivityIdRef\":\"InvokeWorkflowFile_5\",\"IsAdvancedOptionsExpanded\":false,\"Categories\":{\"Common\":true,\"Options\":true,\"Log\":true},\"Widgets\":{}},{\"ActivityIdRef\":\"InvokeWorkflowFile_8\",\"IsAdvancedOptionsExpanded\":false,\"Categories\":{\"Common\":true,\"Options\":true,\"Log\":true},\"Widgets\":{}},{\"ActivityIdRef\":\"LogMessage_3\",\"IsAdvancedOptionsExpanded\":false,\"Widgets\":{}},{\"ActivityIdRef\":\"InvokeWorkflowFile_7\",\"IsAdvancedOptionsExpanded\":false,\"Categories\":{\"Common\":true,\"Options\":true,\"Log\":true},\"Widgets\":{}},{\"ActivityIdRef\":\"Throw_3\",\"IsAdvancedOptionsExpanded\":false,\"Widgets\":{}},{\"ActivityIdRef\":\"InvokeWorkflowFile_2\",\"IsAdvancedOptionsExpanded\":false,\"Categories\":{\"Common\":true,\"Options\":true,\"Log\":true},\"Widgets\":{}},{\"ActivityIdRef\":\"LogMessage_8\",\"IsAdvancedOptionsExpanded\":false,\"Widgets\":{}},{\"ActivityIdRef\":\"InvokeWorkflowFile_6\",\"IsAdvancedOptionsExpanded\":false,\"Categories\":{\"Common\":true,\"Options\":true,\"Log\":true},\"Widgets\":{}},{\"ActivityIdRef\":\"Throw_2\",\"IsAdvancedOptionsExpanded\":false,\"Widgets\":{}}],\"Google/GetCalendarAPI.xaml\":[{\"ActivityIdRef\":\"LogMessage_1\",\"IsAdvancedOptionsExpanded\":false,\"Widgets\":{}},{\"ActivityIdRef\":\"GetEventListConnections_2\",\"IsAdvancedOptionsExpanded\":false,\"Categories\":{\"Options\":true,\"Output\":true},\"Widgets\":{}}]}","Compiler":"2","ProjectWatches":"{\"Value\":[]}"}